<?xml version="1.0" encoding="UTF-8"?>
<databaseChangeLog xmlns="http://www.liquibase.org/xml/ns/dbchangelog"
                   xmlns:xsi="http://www.w3.org/2001/XMLSchema-instance"
                   xsi:schemaLocation="http://www.liquibase.org/xml/ns/dbchangelog
                                       http://www.liquibase.org/xml/ns/dbchangelog/dbchangelog-4.17.xsd">


    <changeSet id="0.17-01" author="Mahdi Rezazadeh">
        <renameTable oldTableName="baseinfo_assessmentkitlike" newTableName="fak_kit_like"/>
    </changeSet>

    <changeSet id="0.17-02" author="Mahdi Rezazadeh">
        <dropColumn tableName="fak_kit_like"
                    columnName="id"/>
    </changeSet>

    <changeSet id="0.17-03" author="Mahnaz Khorsandi">
        <renameColumn tableName="fak_kit_like" oldColumnName="assessment_kit_id" newColumnName="kit_id"/>
    </changeSet>

    <changeSet id="0.17-04" author="Mahdi Rezazadeh">
        <addPrimaryKey tableName="fak_kit_like"
                       columnNames="kit_id, user_id"
                       constraintName="pk_fak_kit_like"/>
    </changeSet>

    <changeSet id="0.17-05" author="Mahdi Rezazadeh">
        <dropAllForeignKeyConstraints baseTableName="fak_kit_like"/>
    </changeSet>

    <changeSet id="0.17-06" author="Mahdi Rezazadeh">
        <addForeignKeyConstraint baseTableName="fak_kit_like"
                                 baseColumnNames="kit_id"
                                 referencedTableName="fak_assessment_kit"
                                 referencedColumnNames="id"
                                 constraintName="fk_fak_kitlike_kit"
                                 deferrable="true" initiallyDeferred="true" onDelete="CASCADE"
                                 validate="true"/>
    </changeSet>

    <changeSet id="0.17-07" author="Mahdi Rezazadeh">
        <addForeignKeyConstraint baseTableName="fak_kit_like"
                                 baseColumnNames="user_id"
                                 referencedTableName="account_user"
                                 referencedColumnNames="id"
                                 constraintName="fk_fak_kitlike_user"
                                 deferrable="true" initiallyDeferred="true" onDelete="CASCADE"
                                 validate="true"/>
    </changeSet>

    <changeSet id="0.17-08" author="Ali Sedaghat">
        <renameTable oldTableName="baseinfo_assessmentkittag" newTableName="fak_kit_tag"/>
    </changeSet>

    <changeSet id="0.17-09" author="Ali Sedaghat">
        <sql>alter table fak_kit_tag rename constraint baseinfo_profiletag_pkey to pk_fak_kit_tag;</sql>
    </changeSet>

    <changeSet id="0.17-10" author="Ali Sedaghat">
        <dropUniqueConstraint constraintName="baseinfo_profiletag_code_4987a4c6_uniq" tableName="fak_kit_tag"/>
    </changeSet>

    <changeSet id="0.17-11" author="Ali Sedaghat">
        <dropUniqueConstraint constraintName="baseinfo_profiletag_title_b2cd9f8a_uniq" tableName="fak_kit_tag"/>
    </changeSet>

    <changeSet id="0.17-12" author="Ali Sedaghat">
        <addUniqueConstraint tableName="fak_kit_tag" columnNames="code" constraintName="uq_fak_kittag_code"/>
    </changeSet>

    <changeSet id="0.17-13" author="Ali Sedaghat">
        <addUniqueConstraint tableName="fak_kit_tag" columnNames="title" constraintName="uq_fak_kittag_title"/>
    </changeSet>

    <changeSet id="0.17-14" author="Ali Sedaghat">
        <renameSequence oldSequenceName="baseinfo_profiletag_id_seq" newSequenceName="fak_kit_tag_id_seq"/>
    </changeSet>

</databaseChangeLog>
